ez_gateway/__init__.py
ez_gateway/conn.py
ez_gateway/errors.py
ez_gateway/opcode.py
ez_gateway-0.1.0.dist-info/LICENSE
ez_gateway-0.1.0.dist-info/WHEEL
ez_gateway-0.1.0.dist-info/METADATA
ez_gateway-0.1.0.dist-info/RECORD
